odoo/addons/mail_show_follower/README.rst
odoo/addons/mail_show_follower/__init__.py
odoo/addons/mail_show_follower/__manifest__.py
odoo/addons/mail_show_follower/models/__init__.py
odoo/addons/mail_show_follower/models/mail_mail.py
odoo/addons/mail_show_follower/models/res_company.py
odoo/addons/mail_show_follower/models/res_config_settings.py
odoo/addons/mail_show_follower/models/res_users.py
odoo/addons/mail_show_follower/static/description/icon.png
odoo/addons/mail_show_follower/views/res_config_settings.xml
odoo/addons/mail_show_follower/views/res_users.xml
odoo13_addon_mail_show_follower-13.0.1.0.1.dev2.dist-info/METADATA
odoo13_addon_mail_show_follower-13.0.1.0.1.dev2.dist-info/WHEEL
odoo13_addon_mail_show_follower-13.0.1.0.1.dev2.dist-info/top_level.txt
odoo13_addon_mail_show_follower-13.0.1.0.1.dev2.dist-info/RECORD
